facebook_business/__init__.py
facebook_business/api.py
facebook_business/apiconfig.py
facebook_business/bootstrap.py
facebook_business/crashreporter.py
facebook_business/exceptions.py
facebook_business/exit_codes.py
facebook_business/fb_ca_chain_bundle.crt
facebook_business/mixins.py
facebook_business/session.py
facebook_business/specs.py
facebook_business/typechecker.py
facebook_business/video_uploader.py
facebook_business/adobjects/__init__.py
facebook_business/adobjects/abstractcrudobject.py
facebook_business/adobjects/abstractobject.py
facebook_business/adobjects/ad.py
facebook_business/adobjects/adaccount.py
facebook_business/adobjects/adaccountactivity.py
facebook_business/adobjects/adaccountadruleshistory.py
facebook_business/adobjects/adaccountadvolume.py
facebook_business/adobjects/adaccountdefaultdestination.py
facebook_business/adobjects/adaccountdefaultobjective.py
facebook_business/adobjects/adaccountdeliveryestimate.py
facebook_business/adobjects/adaccountiosfourteencampaignlimits.py
facebook_business/adobjects/adaccountmatchedsearchapplicationsedgedata.py
facebook_business/adobjects/adaccountmaxbid.py
facebook_business/adobjects/adaccountpromotableobjects.py
facebook_business/adobjects/adaccountreachestimate.py
facebook_business/adobjects/adaccountrecommendedcamapaignbudget.py
facebook_business/adobjects/adaccountsubscribedapps.py
facebook_business/adobjects/adaccounttargetingunified.py
facebook_business/adobjects/adaccounttrackingdata.py
facebook_business/adobjects/adaccountuser.py
facebook_business/adobjects/adactivity.py
facebook_business/adobjects/adassetfeedspec.py
facebook_business/adobjects/adassetfeedspecassetlabel.py
facebook_business/adobjects/adassetfeedspecbody.py
facebook_business/adobjects/adassetfeedspeccaption.py
facebook_business/adobjects/adassetfeedspecdescription.py
facebook_business/adobjects/adassetfeedspecgrouprule.py
facebook_business/adobjects/adassetfeedspecimage.py
facebook_business/adobjects/adassetfeedspeclinkurl.py
trackian_homebew_facebook_business-14.0.0.dist-info/LICENSE.txt
trackian_homebew_facebook_business-14.0.0.dist-info/METADATA
trackian_homebew_facebook_business-14.0.0.dist-info/WHEEL
trackian_homebew_facebook_business-14.0.0.dist-info/top_level.txt
trackian_homebew_facebook_business-14.0.0.dist-info/RECORD
