Metadata-Version: 2.1
Name: trackian-homebew-facebook-business
Version: 14.0.0
Summary: Facebook Business SDK
Home-page: https://github.com/trackian/facebook-python-business-sdk
Download-URL: https://github.com/facebook/facebook-python-business-sdk/tarball/14.0.0
Author: AZ
Author-email: 
License: LICENSE.txt
License-File: LICENSE.txt
Requires-Dist: requests (>=2.3.0)
Requires-Dist: six (>=1.7.3)
Requires-Dist: curlify (>=2.1.0)
Requires-Dist: pycountry (>=19.8.18)
Requires-Dist: enum34 ; python_version < "3.4"
Requires-Dist: aiohttp ; python_version >= "3.5.3"
